suraya/__init__.py
suraya/grafana/__init__.py
suraya/grafana/mk.py
suraya/marimo/__init__.py
suraya/marimo/mk.py
suraya/marimo/serve.py
suraya/marimo/app/__init__.py
suraya/marimo/app/basic.py
suraya/marimo/app/connect.py
suraya/marimo/app/sys.jobs_log.py
suraya/system/__init__.py
suraya/system/mk.py
suraya-0.0.0.dist-info/licenses/LICENSE
suraya-0.0.0.dist-info/METADATA
suraya-0.0.0.dist-info/WHEEL
suraya-0.0.0.dist-info/top_level.txt
suraya-0.0.0.dist-info/RECORD
