Metadata-Version: 2.4
Name: suraya
Version: 0.0.0
Summary: Suraya - a blend of Grafana and Marimo, with flavours of AMG and PMM.
Author-email: Andreas Motl <andreas.motl@panodata.org>
License: AGPL 3, EUPL 1.2
Keywords: amg,cratedb,dash,dashboard,general purpose,grafana,kotori,library,marimo,mixed,plotly,pmm,pyviz,react
Classifier: Development Status :: 1 - Planning
Classifier: Environment :: Console
Classifier: Intended Audience :: Customer Service
Classifier: Intended Audience :: Developers
Classifier: Intended Audience :: Education
Classifier: Intended Audience :: Information Technology
Classifier: Intended Audience :: Telecommunications Industry
Classifier: License :: OSI Approved :: European Union Public Licence 1.2 (EUPL 1.2)
Classifier: License :: OSI Approved :: GNU Affero General Public License v3
Classifier: Operating System :: MacOS :: MacOS X
Classifier: Operating System :: POSIX :: Linux
Classifier: Operating System :: Unix
Classifier: Programming Language :: Python
Classifier: Programming Language :: Python :: 3 :: Only
Classifier: Programming Language :: Python :: 3.11
Classifier: Programming Language :: Python :: 3.12
Classifier: Programming Language :: Python :: 3.13
Classifier: Topic :: Communications
Classifier: Topic :: Education
Classifier: Topic :: Scientific/Engineering :: GIS
Classifier: Topic :: Scientific/Engineering :: Human Machine Interfaces
Classifier: Topic :: Scientific/Engineering :: Information Analysis
Classifier: Topic :: Scientific/Engineering :: Interface Engine/Protocol Translator
Classifier: Topic :: Scientific/Engineering :: Visualization
Classifier: Topic :: Software Development :: Libraries
Classifier: Topic :: Text Processing
Classifier: Topic :: Utilities
Requires-Python: >=3.11
License-File: LICENSE
Requires-Dist: attrs
Requires-Dist: click
Requires-Dist: hishel<0.2
Requires-Dist: munch
Requires-Dist: pueblo
Requires-Dist: pypdl
Requires-Dist: python-on-whales
Provides-Extra: develop
Requires-Dist: pueblo[develop]; extra == "develop"
Provides-Extra: web
Requires-Dist: duckdb; extra == "web"
Requires-Dist: fastapi; extra == "web"
Requires-Dist: jinja2; extra == "web"
Requires-Dist: marimo; extra == "web"
Requires-Dist: pandas==2.2.3; extra == "web"
Requires-Dist: starlette; extra == "web"
Requires-Dist: requests; extra == "web"
Requires-Dist: pydantic; extra == "web"
Requires-Dist: sqlalchemy-cratedb; extra == "web"
Requires-Dist: vega-datasets==0.9.0; extra == "web"
Provides-Extra: test
Requires-Dist: pueblo[testing]; extra == "test"
Dynamic: license-file
